{"id": "scikit_esn_classifier", "path": "d:\\xinze\\Documents\\GitHub\\Stochastic_RNN\\Scikit-ESN\\scikit_esn_classifier.py", "mtime": 1523511535, "size": 10834, "hash": "80a5f2282ab501f38bb0a3479cba14d2", "data_mtime": 1523694935, "dependencies": ["__future__", "builtins", "abc", "typing"], "suppressed": ["sklearn.base", "sklearn.utils", "numpy", "scipy", "scipy.sparse", "sklearn.preprocessing", "sklearn.linear_model", "sklearn.metrics"], "child_modules": [], "options": {"always_true": [], "disallow_untyped_calls": false, "strict_boolean": false, "disallow_any_expr": false, "ignore_errors": false, "disallow_subclassing_any": false, "warn_no_return": true, "disallow_untyped_decorators": false, "no_implicit_optional": false, "disallow_untyped_defs": false, "follow_imports": "silent", "disallow_any_decorated": false, "disallow_any_explicit": false, "cache_fine_grained": false, "platform": "win32", "always_false": [], "quick_and_dirty": false, "ignore_missing_imports": true, "strict_optional_whitelist": null, "strict_optional": false, "disallow_any_unimported": false, "check_untyped_defs": false, "show_none_errors": true, "warn_return_any": false, "warn_unused_ignores": false, "follow_imports_for_stubs": false, "disallow_any_generics": false}, "dep_prios": [5, 5, 30, 30, 5, 5, 5, 5, 5, 5, 5, 5], "dep_lines": [19, 1, 1, 1, 20, 21, 22, 24, 25, 26, 27, 28], "interface_hash": "b4251c9add883c26f8c49628bd8210f3", "version_id": "0.590", "ignore_all": false}
